geneagrapher_core/__init__.py
geneagrapher_core/mathgenealogy-intermediate.pem
geneagrapher_core/py.typed
geneagrapher_core/record.py
geneagrapher_core/traverse.py
geneagrapher_core-0.1.4.dist-info/LICENSE.md
geneagrapher_core-0.1.4.dist-info/METADATA
geneagrapher_core-0.1.4.dist-info/WHEEL
geneagrapher_core-0.1.4.dist-info/RECORD
