Metadata-Version: 2.3
Name: geneagrapher-core
Version: 0.1.4
Summary: Functions for getting records and building graphs from the Math Genealogy Project.
License: MIT
Author: David Alber
Author-email: alber.david@gmail.com
Requires-Python: >=3.11,<4.0
Classifier: License :: OSI Approved :: MIT License
Classifier: Programming Language :: Python :: 3
Classifier: Programming Language :: Python :: 3.11
Classifier: Programming Language :: Python :: 3.12
Classifier: Programming Language :: Python :: 3.13
Requires-Dist: aiodns (>=3.0.0,<4.0.0)
Requires-Dist: aiohttp (>=3.9.3,<4.0.0)
Requires-Dist: beautifulsoup4 (>=4.11.1,<5.0.0)
Requires-Dist: types-beautifulsoup4 (>=4.11.6.4,<5.0.0.0)
Project-URL: Repository, https://github.com/davidalber/geneagrapher-core
